{
  "main": {
    "id": "f6afaea6090b86d1",
    "type": "split",
    "children": [
      {
        "id": "ac5e815bbebeb5fb",
        "type": "tabs",
        "children": [
          {
            "id": "cdadc0c82c84e55e",
            "type": "leaf",
            "state": {
              "type": "excalidraw",
              "state": {
                "file": "aula5/classificacao_instancias.excalidraw.md"
              },
              "icon": "excalidraw-icon",
              "title": "classificacao_instancias.excalidraw"
            }
          }
        ]
      }
    ],
    "direction": "vertical"
  },
  "left": {
    "id": "d2feafeb52e4f2e4",
    "type": "split",
    "children": [
      {
        "id": "f2a7819337570e66",
        "type": "tabs",
        "children": [
          {
            "id": "18ae20b36d79e108",
            "type": "leaf",
            "state": {
              "type": "file-explorer",
              "state": {
                "sortOrder": "alphabetical",
                "autoReveal": false
              },
              "icon": "lucide-folder-closed",
              "title": "Explorador de arquivos"
            }
          },
          {
            "id": "c017e792be8495f1",
            "type": "leaf",
            "state": {
              "type": "search",
              "state": {
                "query": "",
                "matchingCase": false,
                "explainSearch": false,
                "collapseAll": false,
                "extraContext": false,
                "sortOrder": "alphabetical"
              },
              "icon": "lucide-search",
              "title": "Search"
            }
          },
          {
            "id": "85c8059b9ee36fcd",
            "type": "leaf",
            "state": {
              "type": "bookmarks",
              "state": {},
              "icon": "lucide-bookmark",
              "title": "Bookmarks"
            }
          }
        ]
      }
    ],
    "direction": "horizontal",
    "width": 242.5,
    "collapsed": true
  },
  "right": {
    "id": "9fcf42872188b7b3",
    "type": "split",
    "children": [
      {
        "id": "a25e2edefb516ea8",
        "type": "tabs",
        "children": [
          {
            "id": "50d74cbb1b86268f",
            "type": "leaf",
            "state": {
              "type": "backlink",
              "state": {
                "collapseAll": false,
                "extraContext": false,
                "sortOrder": "alphabetical",
                "showSearch": false,
                "searchQuery": "",
                "backlinkCollapsed": false,
                "unlinkedCollapsed": true
              },
              "icon": "links-coming-in",
              "title": "Backlinks"
            }
          },
          {
            "id": "ec9ba002ac1a78ad",
            "type": "leaf",
            "state": {
              "type": "outgoing-link",
              "state": {
                "linksCollapsed": false,
                "unlinkedCollapsed": true
              },
              "icon": "links-going-out",
              "title": "Outgoing links"
            }
          },
          {
            "id": "8f7aafbe1a3d3422",
            "type": "leaf",
            "state": {
              "type": "tag",
              "state": {
                "sortOrder": "frequency",
                "useHierarchy": true,
                "showSearch": false,
                "searchQuery": ""
              },
              "icon": "lucide-tags",
              "title": "Tags"
            }
          },
          {
            "id": "95b0b04fee9d5367",
            "type": "leaf",
            "state": {
              "type": "all-properties",
              "state": {
                "sortOrder": "frequency",
                "showSearch": false,
                "searchQuery": ""
              },
              "icon": "lucide-archive",
              "title": "All properties"
            }
          },
          {
            "id": "229652ea776a79ef",
            "type": "leaf",
            "state": {
              "type": "outline",
              "state": {
                "followCursor": false,
                "showSearch": false,
                "searchQuery": ""
              },
              "icon": "lucide-list",
              "title": "Outline"
            }
          }
        ]
      }
    ],
    "direction": "horizontal",
    "width": 300,
    "collapsed": true
  },
  "left-ribbon": {
    "hiddenItems": {
      "switcher:Abrir a troca rápida": false,
      "graph:Abrir visualização em gráfico": false,
      "canvas:Criar novo canvas": false,
      "daily-notes:Abrir a nota de hoje": false,
      "templates:Inserir modelo": false,
      "command-palette:Abrir paleta de comandos": false,
      "bases:Criar nova base": false,
      "obsidian-excalidraw-plugin:New drawing": false
    }
  },
  "floating": {
    "id": "bb8109b4785735d2",
    "type": "floating",
    "children": [
      {
        "id": "100b5f180d6def59",
        "type": "window",
        "children": [
          {
            "id": "61980d47c7554a49",
            "type": "tabs",
            "children": [
              {
                "id": "4f580d645d523c31",
                "type": "leaf",
                "state": {
                  "type": "excalidraw",
                  "state": {
                    "file": "estudo_p1.excalidraw.md"
                  },
                  "icon": "excalidraw-icon",
                  "title": "estudo_p1.excalidraw"
                }
              }
            ]
          }
        ],
        "direction": "vertical",
        "x": -1253,
        "y": -200,
        "width": 1253,
        "height": 778,
        "maximize": true,
        "zoom": 0
      }
    ]
  },
  "active": "4f580d645d523c31",
  "lastOpenFiles": [
    "aula5/classificacao_instancias.excalidraw.md",
    "estudo_p1.excalidraw.md",
    "media/Pasted Image 20260407204612_820.png",
    "aula10/arvore_decisao.excalidraw.md",
    "aula6/bayesiana.excalidraw.md",
    "aula8/classificadores_lineares.excalidraw.md",
    "aula7/gaussian_mixture_models.excalidraw.md",
    "aula9/support_vector_machines.excalidraw.md",
    "aula4/validacao.excalidraw",
    "aula2/engenharia_de_caracteristicas.excalidraw.md",
    "aula3/representacao-audio.excalidraw",
    "aula3/representacao-imagem.excalidraw",
    "aula3/representacao-texto.excalidraw",
    "aula4/metricas.excalidraw",
    "aula4/bias-variance.excalidraw",
    "README.md",
    "media/Pasted Image 20260407204743_089.png",
    "media/Pasted Image 20260407204727_415.png",
    "media/Pasted Image 20260407204712_382.png",
    "media/Pasted Image 20260407204632_409.png",
    "media/Pasted Image 20260407204557_588.png",
    "Pasted Image 20260407204540_945.png",
    "media/Pasted Image 20260407204513_221.png",
    "media/Pasted Image 20260407204302_659.png",
    "media/Pasted Image 20260407204238_711.png",
    "Excalidraw",
    "aula4/benchmark_avaliacao_continua.excalidraw.md",
    "aula2/engenharia_de_caracteristicas.excalidraw",
    "aula10",
    "aula9",
    "Untitled.md"
  ]
}